gurobipy_pandas/__init__.py
gurobipy_pandas/accessors.py
gurobipy_pandas/api.py
gurobipy_pandas/constraints.py
gurobipy_pandas/index_mappers.py
gurobipy_pandas/py.typed
gurobipy_pandas/util.py
gurobipy_pandas/variables.py
gurobipy_pandas-1.2.0.dist-info/METADATA
gurobipy_pandas-1.2.0.dist-info/WHEEL
gurobipy_pandas-1.2.0.dist-info/licenses/LICENSE
gurobipy_pandas-1.2.0.dist-info/RECORD
