Metadata-Version: 2.3
Name: gurobipy-pandas
Version: 1.2.0
Summary: Pandas accessors for gurobipy interaction
Project-URL: Documentation, https://gurobi-optimization-gurobipy-pandas.readthedocs-hosted.com/en/latest
Project-URL: Issues, https://github.com/Gurobi/gurobipy-pandas/issues
Project-URL: Source, https://github.com/Gurobi/gurobipy-pandas
Author-email: Simon Bowly <bowly@gurobi.com>, Robert Luce <luce@gurobi.com>
License: Apache-2.0
Keywords: gurobipy,optimization,pandas
Classifier: Development Status :: 5 - Production/Stable
Classifier: Operating System :: OS Independent
Classifier: Programming Language :: Python :: 3
Classifier: Programming Language :: Python :: 3.8
Classifier: Programming Language :: Python :: 3.9
Classifier: Programming Language :: Python :: 3.10
Classifier: Programming Language :: Python :: 3.11
Classifier: Programming Language :: Python :: 3.12
Classifier: Programming Language :: Python :: Implementation :: CPython
Requires-Python: >=3.8
Requires-Dist: gurobipy>=9.1
Requires-Dist: pandas>=1.0
